[{"line":1,"elements":[{"line":2,"name":"","description":"","type":"background","keyword":"Background","steps":[{"result":{"duration":11650213400,"status":"passed"},"line":3,"name":"user on Target Homepage","match":{"location":"stepDef.loginSteps.userOnTargetHomepage()"},"keyword":"Given "}]},{"start_timestamp":"2023-06-14T01:10:14.561Z","before":[{"result":{"duration":3564598600,"status":"passed"},"match":{"location":"stepDef.loginSteps.setup()"}}],"line":6,"name":"user should be able to login with valid credentials","description":"","id":"login-feature;user-should-be-able-to-login-with-valid-credentials","after":[{"result":{"duration":996200,"status":"passed"},"match":{"location":"stepDef.loginSteps.teardown()"}}],"type":"scenario","keyword":"Scenario","steps":[{"result":{"duration":987632200,"status":"passed"},"line":7,"name":"user enter valid email address","match":{"location":"stepDef.loginSteps.user_enter_valid_email_address()"},"keyword":"And "},{"result":{"duration":193786600,"status":"passed"},"line":8,"name":"user enter valid password","match":{"location":"stepDef.loginSteps.user_enter_valid_password()"},"keyword":"And "},{"result":{"duration":78790200,"status":"passed"},"line":9,"name":"user clicks on Log In button","match":{"location":"stepDef.loginSteps.user_clicks_on_log_in_button()"},"keyword":"When "},{"result":{"duration":6796642300,"status":"passed"},"line":10,"name":"user should be able to successfully login","match":{"location":"stepDef.loginSteps.user_should_be_able_to_successfully_login()"},"keyword":"Then "}],"tags":[{"name":"@smoke"}]},{"line":2,"name":"","description":"","type":"background","keyword":"Background","steps":[{"result":{"duration":68010917200,"status":"passed"},"line":3,"name":"user on Target Homepage","match":{"location":"stepDef.loginSteps.userOnTargetHomepage()"},"keyword":"Given "}]},{"start_timestamp":"2023-06-14T01:10:37.875Z","before":[{"result":{"duration":2828968700,"status":"passed"},"match":{"location":"stepDef.loginSteps.setup()"}}],"line":15,"name":"User should not be able to login with valid email and invalid password","description":"","id":"login-feature;user-should-not-be-able-to-login-with-valid-email-and-invalid-password","after":[{"result":{"status":"passed"},"match":{"location":"stepDef.loginSteps.teardown()"}}],"type":"scenario","keyword":"Scenario","steps":[{"result":{"duration":1676447800,"status":"passed"},"line":16,"name":"user enter valid email address","match":{"location":"stepDef.loginSteps.user_enter_valid_email_address()"},"keyword":"And "},{"result":{"duration":258363100,"status":"passed"},"line":17,"name":"user enter invalid password","match":{"location":"stepDef.loginSteps.userEnterInvalidPassword()"},"keyword":"And "},{"result":{"duration":85423000,"status":"passed"},"line":18,"name":"user clicks on Log In button","match":{"location":"stepDef.loginSteps.user_clicks_on_log_in_button()"},"keyword":"When "},{"result":{"duration":629543400,"status":"passed"},"line":19,"name":"user should be able see \"hat password is incorrect\" message","match":{"arguments":[{"val":"\"hat password is incorrect\"","offset":24}],"location":"stepDef.loginSteps.userShouldBeAbleSeeMessage(java.lang.String)"},"keyword":"Then "}],"tags":[{"name":"@smoke"}]},{"line":2,"name":"","description":"","type":"background","keyword":"Background","steps":[{"result":{"duration":12842247500,"status":"passed"},"line":3,"name":"user on Target Homepage","match":{"location":"stepDef.loginSteps.userOnTargetHomepage()"},"keyword":"Given "}]},{"start_timestamp":"2023-06-14T01:11:51.373Z","before":[{"result":{"duration":2469919000,"status":"passed"},"match":{"location":"stepDef.loginSteps.setup()"}}],"line":21,"name":"User should not be able to login with invalid email and valid password","description":"","id":"login-feature;user-should-not-be-able-to-login-with-invalid-email-and-valid-password","after":[{"result":{"status":"passed"},"match":{"location":"stepDef.loginSteps.teardown()"}}],"type":"scenario","keyword":"Scenario","steps":[{"result":{"duration":1709426000,"status":"passed"},"line":22,"name":"user enter invalid email address","match":{"location":"stepDef.loginSteps.userEnterInvalidEmailAddress()"},"keyword":"And "},{"result":{"duration":329120700,"status":"passed"},"line":23,"name":"user enter valid password","match":{"location":"stepDef.loginSteps.user_enter_valid_password()"},"keyword":"And "},{"result":{"duration":176535000,"status":"passed"},"line":24,"name":"user clicks on Log In button","match":{"location":"stepDef.loginSteps.user_clicks_on_log_in_button()"},"keyword":"When "},{"result":{"duration":795861800,"status":"passed"},"line":25,"name":"user should be able see \"e can't find your account\" message","match":{"arguments":[{"val":"\"e can't find your account\"","offset":24}],"location":"stepDef.loginSteps.userShouldBeAbleSeeMessage(java.lang.String)"},"keyword":"Then "}],"tags":[{"name":"@smoke"}]},{"line":2,"name":"","description":"","type":"background","keyword":"Background","steps":[{"result":{"duration":15317498300,"status":"passed"},"line":3,"name":"user on Target Homepage","match":{"location":"stepDef.loginSteps.userOnTargetHomepage()"},"keyword":"Given "}]},{"start_timestamp":"2023-06-14T01:12:09.703Z","before":[{"result":{"duration":2174961000,"status":"passed"},"match":{"location":"stepDef.loginSteps.setup()"}}],"line":27,"name":"User should not be able to login with invalid email and password","description":"","id":"login-feature;user-should-not-be-able-to-login-with-invalid-email-and-password","after":[{"result":{"status":"passed"},"match":{"location":"stepDef.loginSteps.teardown()"}}],"type":"scenario","keyword":"Scenario","steps":[{"result":{"duration":2015606800,"status":"passed"},"line":28,"name":"user enter invalid email address","match":{"location":"stepDef.loginSteps.userEnterInvalidEmailAddress()"},"keyword":"And "},{"result":{"duration":278254900,"status":"passed"},"line":29,"name":"user enter invalid password","match":{"location":"stepDef.loginSteps.userEnterInvalidPassword()"},"keyword":"And "},{"result":{"duration":134639200,"status":"passed"},"line":30,"name":"user clicks on Log In button","match":{"location":"stepDef.loginSteps.user_clicks_on_log_in_button()"},"keyword":"When "},{"result":{"duration":788938900,"status":"passed"},"line":31,"name":"user should be able see \"e can't find your account\" message","match":{"arguments":[{"val":"\"e can't find your account\"","offset":24}],"location":"stepDef.loginSteps.userShouldBeAbleSeeMessage(java.lang.String)"},"keyword":"Then "}],"tags":[{"name":"@smoke"}]}],"name":"Login Feature","description":"","id":"login-feature","keyword":"Feature","uri":"file:src/test/java/features/login.feature","tags":[]},{"line":1,"elements":[{"start_timestamp":"2023-06-14T01:12:30.421Z","before":[{"result":{"duration":2293562100,"status":"passed"},"match":{"location":"stepDef.loginSteps.setup()"}}],"line":4,"name":"User should be able to create a brand new account with unique email address","description":"","id":"signup-feature;user-should-be-able-to-create-a-brand-new-account-with-unique-email-address","after":[{"result":{"status":"passed"},"match":{"location":"stepDef.loginSteps.teardown()"}}],"type":"scenario","keyword":"Scenario","steps":[{"result":{"duration":15921174800,"status":"passed"},"line":5,"name":"user on Target Homepage","match":{"location":"stepDef.loginSteps.userOnTargetHomepage()"},"keyword":"Given "},{"result":{"duration":1122571400,"status":"passed"},"line":6,"name":"user clicks on \"Create new account\" button","match":{"arguments":[{"val":"\"Create new account\"","offset":15}],"location":"stepDef.SignupSteps.user_clicks_on_button(java.lang.String)"},"keyword":"And "},{"result":{"duration":755972200,"status":"passed"},"line":7,"name":"user enter their valid email address","match":{"location":"stepDef.SignupSteps.user_enter_their_valid_email_address()"},"keyword":"And "},{"result":{"duration":365601000,"status":"passed"},"line":8,"name":"user enters First and Last Name","match":{"location":"stepDef.SignupSteps.user_enters_first_and_last_name()"},"keyword":"And "},{"result":{"duration":216488100,"status":"passed"},"line":9,"name":"user enter Password","match":{"location":"stepDef.SignupSteps.user_enter_password()"},"keyword":"And "},{"result":{"duration":119679800,"status":"passed"},"line":10,"name":"user clicks on Create my account button","match":{"location":"stepDef.SignupSteps.userClicksOnCreateMyAccountButton()"},"keyword":"When "},{"result":{"duration":1180269300,"status":"passed"},"line":11,"name":"user clicks on \"Join free\"","match":{"arguments":[{"val":"\"Join free\"","offset":15}],"location":"stepDef.SignupSteps.userClicksOn(java.lang.String)"},"keyword":"And "},{"result":{"duration":11969900,"status":"passed"},"line":12,"name":"user should be able to successfully Create Target Account","match":{"location":"stepDef.SignupSteps.userShouldBeAbleToSuccessfullyCreateTargetAccount()"},"keyword":"Then "}],"tags":[{"name":"@smoke"}]}],"name":"Signup Feature","description":"","id":"signup-feature","keyword":"Feature","uri":"file:src/test/java/features/signup.feature","tags":[]}]